optimum/amd/__init__.py
optimum/amd/cli.py
optimum/amd/topology_utils.py
optimum/amd/version.py
optimum/amd/ryzenai/__init__.py
optimum/amd/ryzenai/configuration.py
optimum/amd/ryzenai/modeling.py
optimum/amd/ryzenai/quantization.py
optimum/amd/ryzenai/utils.py
optimum_amd-0.1.0.dist-info/LICENSE
optimum_amd-0.1.0.dist-info/METADATA
optimum_amd-0.1.0.dist-info/WHEEL
optimum_amd-0.1.0.dist-info/entry_points.txt
optimum_amd-0.1.0.dist-info/top_level.txt
optimum_amd-0.1.0.dist-info/RECORD
