Metadata-Version: 2.1
Name: optimum-amd
Version: 0.1.0
Summary: Optimum Library is an extension of the Hugging Face Transformers library, providing a framework to integrate third-party libraries from Hardware Partners and interface with their specific functionality.
Home-page: https://github.com/huggingface/optimum-amd
Author: HuggingFace Inc. Special Ops Team
Author-email: hardware@huggingface.co
License: MIT
Keywords: transformers,amd,ryzen,ipu,quantization,on-device,instinct
Classifier: Development Status :: 5 - Production/Stable
Classifier: License :: OSI Approved :: Apache Software License
Classifier: Intended Audience :: Developers
Classifier: Intended Audience :: Education
Classifier: Intended Audience :: Science/Research
Classifier: Operating System :: OS Independent
Classifier: Programming Language :: Python :: 3.8
Classifier: Programming Language :: Python :: 3.9
Classifier: Programming Language :: Python :: 3.10
Classifier: Programming Language :: Python :: 3.11
Classifier: Topic :: Scientific/Engineering :: Artificial Intelligence
License-File: LICENSE
Requires-Dist: optimum
Requires-Dist: transformers
Requires-Dist: onnx
Requires-Dist: onnxruntime <1.16.0
Requires-Dist: onnxruntime-extensions
Provides-Extra: quality
Requires-Dist: black ~=23.1 ; extra == 'quality'
Requires-Dist: ruff <=0.0.259,>=0.0.241 ; extra == 'quality'
Provides-Extra: tests
Requires-Dist: pytest ; extra == 'tests'
Requires-Dist: parameterized ; extra == 'tests'
